ltransf/__init__.py
ltransf/stack.py
ltransf/additivestack/__init__.py
ltransf/additivestack/additivestack.py
ltransf/definitions/__init__.py
ltransf/definitions/position.py
ltransf/definitions/symbol.py
ltransf/definitions/token.py
ltransf/definitions/tokenclass.py
ltransf/definitions/tokentype.py
ltransf/errors/__init__.py
ltransf/errors/errors.py
ltransf/expression_nodes/__init__.py
ltransf/expression_nodes/binarynode.py
ltransf/expression_nodes/constevalconst_expnode.py
ltransf/expression_nodes/constmultipoly_expnode.py
ltransf/expression_nodes/exponential_expnode.py
ltransf/expression_nodes/linearpoly_expnode.py
ltransf/expression_nodes/power1_expnode.py
ltransf/expression_nodes/powern_expnode.py
ltransf/expression_nodes/trigfunc_expnode.py
ltransf/expression_nodes/udfunc_expnode.py
ltransf/laplace/__init__.py
ltransf/laplace/laplaceof.py
ltransf/laplace/laplacesort.py
ltransf/laplace/lextokenfunc_ltrans.py
ltransf/laplace/ltrans.py
ltransf/laplace/powernfunc_ltrans.py
ltransf/laplace/trigfunc_ltrans.py
ltransf/laplace/udfunc_ltrans.py
ltransf/lexer/__init__.py
ltransf/lexer/lexer.py
ltransf/parser/__init__.py
ltransf/parser/parser.py
ltransf-0.0.2.dist-info/LICENSE.txt
ltransf-0.0.2.dist-info/METADATA
ltransf-0.0.2.dist-info/WHEEL
ltransf-0.0.2.dist-info/top_level.txt
ltransf-0.0.2.dist-info/RECORD
