Metadata-Version: 2.1
Name: ltransf
Version: 0.0.2
Summary: Symbolic solver for Laplace transforms
Home-page: https://github.com/tgashwinkumar/ltransf
Author: tgashwinkumar
Author-email: tgashwinkumar@gmail.com
License: UNKNOWN
Project-URL: Bug Tracker, https://github.com/tgashwinkumar/ltransf/issues
Platform: UNKNOWN
Classifier: Programming Language :: Python :: 3
Classifier: License :: OSI Approved :: MIT License
Classifier: Operating System :: OS Independent
Requires-Python: >=3.7
License-File: LICENSE.txt
